autora/experimentalist/mixture/__init__.py
mixture_experimentalist-1.0.0a7.dist-info/LICENSE
mixture_experimentalist-1.0.0a7.dist-info/METADATA
mixture_experimentalist-1.0.0a7.dist-info/WHEEL
mixture_experimentalist-1.0.0a7.dist-info/top_level.txt
mixture_experimentalist-1.0.0a7.dist-info/RECORD
