Metadata-Version: 2.1
Name: mixture-experimentalist
Version: 1.0.0a7
Summary: The goal of this project is to examine the performance of a mixture experimentalist–a hybrid of different experimental sampling strategies–in terms of its ability to recover a ground-truth model from synthetic data.
Author-email: Marina Dubova <marina.dubova.97@gmail.com>
License: MIT license
Project-URL: homepage, http://www.empiricalresearch.ai
Project-URL: repository, https://github.com/blinodelka/mixture_experimental_strategies
Project-URL: documentation, https://autoresearch.github.io/autora/
Requires-Python: <4,>=3.8
License-File: LICENSE
Requires-Dist: autora-core
Requires-Dist: typing
Requires-Dist: numpy
Requires-Dist: pandas
Provides-Extra: dev
Requires-Dist: autora-core[dev] ; extra == 'dev'
